mediaDB/API.py
mediaDB/Database.py
mediaDB/__init__.py
mediaDB/common.py
mediaDB/exceptions.py
mediaDB/flaresolver.py
mediaDB/indexer.py
mediaDB/mediaTypes.py
mediaDB/metaProviders.py
mediaDB/settings.py
mediaDB/test.py
mediaDB/tmdb.py
mediaDB/extension/__init__.py
mediaDB/extension/Indexers/Yggtorrent.py
mediaDB/extension/Indexers/__init__.py
mediaDB/extension/Indexers/common.py
mediaDB/extension/Indexers/nyaa.py
mediaDB/extension/Providers/__init__.py
mediaDB/extension/Providers/common.py
mediaDB/extension/Providers/tmdb.py
mediaDB/extension/indexers/__init__.py
mediaDB/extension/indexers/common.py
mediaDB/extension/indexers/tmdb.py
mediaDB-0.0.4.2.dist-info/METADATA
mediaDB-0.0.4.2.dist-info/WHEEL
mediaDB-0.0.4.2.dist-info/top_level.txt
mediaDB-0.0.4.2.dist-info/RECORD
