Metadata-Version: 2.1
Name: mediaDB
Version: 0.0.4.2
Summary: Database to manage media
Author: Benjamin Roget
Author-email: benjamin.rogetpro@gmail.com
Keywords: python,media,manage
Classifier: Development Status :: 1 - Planning
Classifier: Intended Audience :: Education
Classifier: Programming Language :: Python :: 3
Classifier: Operating System :: POSIX :: Linux 
Classifier: Framework :: Flask 
Classifier: License :: Free For Home Use 
